gatf/__init__.py
gatf/algorithms.py
gatf/operators.py
gatf/population.py
gatf-0.3.2.dist-info/LICENSE
gatf-0.3.2.dist-info/METADATA
gatf-0.3.2.dist-info/WHEEL
gatf-0.3.2.dist-info/top_level.txt
gatf-0.3.2.dist-info/RECORD
