Metadata-Version: 2.1
Name: gatf
Version: 0.3.2
Summary: A small library of single and multi-objective genetic algorithms build with Tensorflow
Author-email: John Edgar <edgarjohnmichael@gmail.com>
License: MIT License        
Project-URL: Homepage, https://gitlab.com/edgarj/gatf
Project-URL: Bug Tracker, https://gitlab.com/edgarj/gatf/issues
Classifier: Programming Language :: Python :: 3
Classifier: License :: OSI Approved :: MIT License
Requires-Python: >=3.7
License-File: LICENSE
